{"concepts":[{"id":"JUR001","name":"Jurisdictional Registry Client Issue","codeSystemId":"https://fhir.infoway-inforoute.ca/CodeSystem/JurisdictionalErrors","codeSystemName":"JurisdictionalErrors","enDisplayName":"Jurisdictional Registry Client Issue","effectiveDate":"20190916","active":true,"subsets":[],"associations":[],"properties":{}},{"id":"JUR002","name":"Jursidictional DIS Client Issue","codeSystemId":"https://fhir.infoway-inforoute.ca/CodeSystem/JurisdictionalErrors","codeSystemName":"JurisdictionalErrors","enDisplayName":"Jursidictional DIS Client Issue","effectiveDate":"20190916","active":true,"subsets":[],"associations":[],"properties":{}},{"id":"JUR003","name":"Connector Client Issue","codeSystemId":"https://fhir.infoway-inforoute.ca/CodeSystem/JurisdictionalErrors","codeSystemName":"JurisdictionalErrors","enDisplayName":"Connector Client Issue","effectiveDate":"20190916","active":true,"subsets":[],"associations":[],"properties":{}},{"id":"JUR004","name":"Jurisdictional Registry Server Issue for Registry requests","codeSystemId":"https://fhir.infoway-inforoute.ca/CodeSystem/JurisdictionalErrors","codeSystemName":"JurisdictionalErrors","enDisplayName":"Jurisdictional Registry Server Issue for Registry requests","effectiveDate":"20190916","active":true,"subsets":[],"associations":[],"properties":{}},{"id":"JUR005","name":"Jurisdictional DIS Server Issue for DIS requests","codeSystemId":"https://fhir.infoway-inforoute.ca/CodeSystem/JurisdictionalErrors","codeSystemName":"JurisdictionalErrors","enDisplayName":"Jurisdictional DIS Server Issue for DIS requests","effectiveDate":"20190916","active":true,"subsets":[],"associations":[],"properties":{}}],"pagination":{"currentPage":1,"totalPages":1,"pageSize":100000,"totalRecords":5,"firstRecord":1,"lastRecord":5,"nextPage":-1,"nextRecord":-1}}