{"id":"2.16.840.1.113883.2.20.3.448","url":"https://tgateway.infoway-inforoute.ca/vs/bundletype","fhirUri":"https://fhir.infoway-inforoute.ca/ValueSet/bundletype","name":"BundleType","versionId":"20190315","effectiveDate":"20190315","publicationTime":"2019031515:25:47","description":"Indicates the purpose of a bundle - how it was intended to be used.","status":"active","codeSystems":[{"id":"2.16.840.1.113883.4.642.3.620","name":"BundleType","businessName":"BundleType","url":"http://hl7.org/fhir/ValueSet/bundle-type","version":"1.4.0"}]}