{"id":"2.16.840.1.113883.2.20.3.487","name":"IndicationForUseControlledSubstance","url":"https://tgateway.infoway-inforoute.ca/vs/indicationforusecontrolledsubstance","fhirUri":"https://fhir.infoway-inforoute.ca/ValueSet/indicationforusecontrolledsubstance","versionId":"20240220","effectiveDate":"20240220","publicationTime":"2024022111:46:07","description":"The clinical reason for which a medication is being ordered. This is a subset of indications for use that are allowed within a tracked or monitored prescription program.","status":"active","category":"SNOMED CT","domains":["ePrescribe"],"properties":{},"owner":"Canada Health Infoway","tags":[],"terminologies":{},"type":"extensional","viewer":"singlesubset","codeSystems":[{"id":"2.16.840.1.113883.6.96","name":"SNOMED CT CA Edition","businessName":"SNOMED CT CA Edition","url":"http://snomed.info/sct","version":"20230930"}],"concepts":[{"id":"103735009","name":"Palliative care (regime/therapy)","codeSystemId":"http://snomed.info/sct","codeSystemName":"SNOMED CT CA Edition","enDisplayName":"Palliative care","frDisplayName":"soins palliatifs","effectiveDate":"20240220","active":true,"subsets":[],"associations":[],"properties":{}},{"id":"213299007","name":"Postoperative pain (finding)","codeSystemId":"http://snomed.info/sct","codeSystemName":"SNOMED CT CA Edition","enDisplayName":"Postoperative pain","frDisplayName":"douleur postopératoire","effectiveDate":"20240220","active":true,"subsets":[],"associations":[],"properties":{}},{"id":"247398009","name":"Neuropathic pain (finding)","codeSystemId":"http://snomed.info/sct","codeSystemName":"SNOMED CT CA Edition","enDisplayName":"Neuropathic pain","frDisplayName":"douleur neuropathique","effectiveDate":"20240220","active":true,"subsets":[],"associations":[],"properties":{}},{"id":"25064002","name":"Headache (finding)","codeSystemId":"http://snomed.info/sct","codeSystemName":"SNOMED CT CA Edition","enDisplayName":"Headache","frDisplayName":"mal de tête","effectiveDate":"20240220","active":true,"subsets":[],"associations":[],"properties":{}},{"id":"274663001","name":"Acute pain (finding)","codeSystemId":"http://snomed.info/sct","codeSystemName":"SNOMED CT CA Edition","enDisplayName":"Acute pain","frDisplayName":"douleur aiguë","effectiveDate":"20240220","active":true,"subsets":[],"associations":[],"properties":{}},{"id":"363346000","name":"Malignant neoplastic disease (disorder)","codeSystemId":"http://snomed.info/sct","codeSystemName":"SNOMED CT CA Edition","enDisplayName":"Cancer","frDisplayName":"cancer","effectiveDate":"20240220","active":true,"subsets":[],"associations":[],"properties":{}},{"id":"385989002","name":"Substance use therapy (regime/therapy)","codeSystemId":"http://snomed.info/sct","codeSystemName":"SNOMED CT CA Edition","enDisplayName":"Substance use therapy","frDisplayName":"traitement de la toxicomanie","effectiveDate":"20240220","active":true,"subsets":[],"associations":[],"properties":{}},{"id":"762452003","name":"Chronic musculoskeletal pain (finding)","codeSystemId":"http://snomed.info/sct","codeSystemName":"SNOMED CT CA Edition","enDisplayName":"Chronic musculoskeletal pain","frDisplayName":"douleur musculosquelettique chronique","effectiveDate":"20240220","active":true,"subsets":[],"associations":[],"properties":{}}]}